{"46": "Adriel Fuentes", "55": "Aguasanta Muñoz", "28": "Alejandra Carrasco", "69": "Amarys Mendoza", "25": "Andrea Cárdenas", "35": "Angelo Gutierrez", "60": "Angie Espinoza", "29": "Aníbal Berríos", "13": "ANTO A", "70": "Antonia Iglesias", "22": "Barbara Acuña", "23": "Barbara Acuña Vidal", "57": "Bryan Orellana", "54": "Camila Bascuñán", "62": "Catalina Novoa", "27": "Claudia Gallegos", "34": "Claudio Jara", "66": "Cristobal Fuentes", "19": "Cristobal Manriquez", "61": "Danae Paredes", "71": "Daniela Álvarez", "30": "DANIELA  SOCORRO", "65": "Davor Fabijancic", "16": "Diana  Marulanda", "17": "Diana Marulanda", "6": "Diego  Acuña", "20": "Fabian Castro", "68": "Fernanda Figueroa", "40": "Flapp Flapp", "72": "Heidi Furlong", "26": "Isidora Contreras", "8": "Joaquin Yanten", "9": "Joaquin Yanten", "12": "Joaquin Yanten", "59": "Jorge Fernández", "39": "Jorge Olivares", "63": "Jose MC", "44": "José Morales Cetino", "36": "Luciana Quijada", "47": "Macarena Núñez", "49": "Magdalena Arancibia", "50": "Magdalena Arancibia", "42": "Makarena Torres", "38": "Manuel Guerra", "33": "Marina Lázzaro", "43": "Millaray Rojas", "14": "Nacho  Morales", "21": "Nicolás Astorga", "10": "Nur Faride", "18": "Paloma Ahumada", "45": "Pamela Fuentes", "5": "Paola  Armas", "51": "Paulina Guerra", "64": "Paulina Guerra", "3": "Pedro  Donoso", "41": "Piera Perinetti", "58": "Piera  Perinetti", "31": "PLAZA VESPUCIO", "4": "Rafa Waingarten", "11": "Rafaela Waingarten", "32": "Rebeca Álvarez", "52": "Rodrigo Aguilera", "15": "Rolando San Martin", "7": "Sofia  S", "1": "Soporte  bsale", "53": "Tania Díaz", "56": "Tiara Barrientos", "24": "TIARE SILVA", "2": "Tomas Lopez", "48": "Valeria Lorca", "37": "Vicente Ponce", "67": "Victoria Yañez"}